govee_H613_BTcontroller/__init__.py
govee_H613_BTcontroller/constants.py
govee_H613_BTcontroller/govee_H613_BTcontroller.py
govee_H613_BTcontroller/utils.py
govee_H613_BTcontroller-1.0.2.dist-info/LICENSE
govee_H613_BTcontroller-1.0.2.dist-info/METADATA
govee_H613_BTcontroller-1.0.2.dist-info/WHEEL
govee_H613_BTcontroller-1.0.2.dist-info/top_level.txt
govee_H613_BTcontroller-1.0.2.dist-info/RECORD
