Metadata-Version: 2.1
Name: govee_H613_BTcontroller
Version: 1.0.2
Summary: A Python library for controlling Govee H613 Bluetooth LED strip.
Home-page: https://github.com/Xample33/govee_H613_BTcontroller
Author: Xample33
Maintainer: Xample33
License: MIT
Keywords: govee bluetooth led strip H613
Classifier: Development Status :: 5 - Production/Stable
Classifier: Programming Language :: Python
Classifier: Programming Language :: Python :: 3
Classifier: Programming Language :: Python :: 3.9
Classifier: Programming Language :: Python :: 3.10
Classifier: Programming Language :: Python :: 3.11
Classifier: Operating System :: OS Independent
Requires-Python: >=3.9
License-File: LICENSE
Requires-Dist: bleak
